{
  "genre": "racing",
  "title": "Racing",
  "games": [
    {
      "slug": "time-trial",
      "title": "Time Trial",
      "path": "games/time-trial/",
      "icon": "🏁",
      "color": "#f2c14e",
      "dims": "3D",
      "tags": ["circuit", "checkpoints", "time-trial", "three.js"],
      "license": "MIT",
      "credit": "Gamf original"
    },
    {
      "slug": "drift-circuit",
      "title": "Drift Circuit",
      "path": "games/drift-circuit/",
      "icon": "🏁",
      "color": "#f2c14e",
      "dims": "2D",
      "tags": ["drift", "time-trial", "coins"],
      "license": "MIT",
      "credit": "Gamf original"
    },
    {
      "slug": "highway",
      "title": "Highway",
      "path": "games/highway/",
      "icon": "🏎️",
      "color": "#f2c14e",
      "dims": "3D",
      "tags": ["steer", "dodge", "endless"],
      "license": "MIT",
      "credit": "Gamf sample"
    },
    {
      "slug": "rally",
      "title": "Rally Stage",
      "path": "games/rally/",
      "icon": "🚙",
      "color": "#f2c14e",
      "dims": "3D",
      "tags": ["rally", "checkpoints", "drift", "three.js"],
      "license": "MIT",
      "credit": "Gamf original"
    }
  ]
}
